gas_detection/__init__.py
gas_detection/__main__.py
gas_detection-1.0.1.dist-info/LICENSE
gas_detection-1.0.1.dist-info/METADATA
gas_detection-1.0.1.dist-info/WHEEL
gas_detection-1.0.1.dist-info/entry_points.txt
gas_detection-1.0.1.dist-info/top_level.txt
gas_detection-1.0.1.dist-info/RECORD
