Metadata-Version: 2.1
Name: gas-detection
Version: 1.0.1
Summary: Gas detection for Raspberry Pi using ADS1x15 and MQ-2 sensors
Home-page: https://github.com/filips123/GasDetection/
Author: Filip Š
Author-email: projects@filips.si
License: GPLv3+
Keywords: smoke gas detection hardware ads1x115 mq2 RaspberryPi
Platform: Linux
Classifier: Development Status :: 5 - Production/Stable
Classifier: Intended Audience :: Education
Classifier: Intended Audience :: Science/Research
Classifier: License :: OSI Approved :: GNU General Public License v3 or later (GPLv3+)
Classifier: Operating System :: Unix
Classifier: Programming Language :: Python :: 3
Classifier: Topic :: Scientific/Engineering :: Physics
Classifier: Topic :: System :: Hardware
Requires-Python: >= 3.4
Provides-Extra: lint
